testlibcreation/__init__.py
testlibcreation/testlibcreation.py
testlibcreation-0.0.2.dist-info/LICENSE
testlibcreation-0.0.2.dist-info/METADATA
testlibcreation-0.0.2.dist-info/WHEEL
testlibcreation-0.0.2.dist-info/top_level.txt
testlibcreation-0.0.2.dist-info/RECORD
