Metadata-Version: 2.1
Name: testlibcreation
Version: 0.0.2
Summary: A package to convert your Jupyter Notebook
Home-page: https://github.com/SergeyZamyatin1/testlibcreation
Author: Sergey Zamyatin
Author-email: sergey.zamyatin.01@list.ru
License: UNKNOWN
Platform: UNKNOWN
Classifier: Programming Language :: Python :: 3.7
Classifier: License :: OSI Approved :: GNU General Public License v3 (GPLv3)
License-File: LICENSE
